LICENSE.txt
MANIFEST.in
README.md
VERSION
setup.cfg
setup.py
./deepracer_compat_reward_function/__init__.py
./deepracer_compat_reward_function/compat_reward_function.py
./deepracer_compat_reward_function/reward_function_wrapper.py
./deepracer_compat_reward_function/utils.py
./deepracer_compat_reward_function/converter/__init__.py
./deepracer_compat_reward_function/converter/agent_converter.py
./deepracer_compat_reward_function/converter/object_converter.py
./deepracer_compat_reward_function/converter/state_converter_interface.py
./deepracer_compat_reward_function/converter/track_converter.py
deepracer_compat_reward_function.egg-info/PKG-INFO
deepracer_compat_reward_function.egg-info/SOURCES.txt
deepracer_compat_reward_function.egg-info/dependency_links.txt
deepracer_compat_reward_function.egg-info/requires.txt
deepracer_compat_reward_function.egg-info/top_level.txt
test/test_compat_reward_function.py
test/test_reward_function_wrapper.py
test/test_utils.py